jobskape/__init__.py
jobskape/dataset_evaluation.py
jobskape/experiment.py
jobskape/gen_prompt_template.py
jobskape/generator.py
jobskape/annotator/feedback.py
jobskape/annotator/feedback_prompt_template.py
jobskape/models/skillExtract/prompt_template.py
jobskape/models/skillExtract/utils.py
jobskape/models/supervised/multilabel_classifier.py
jobskape/utils/gen_utils.py
jobskape-0.0.2.dist-info/LICENSE
jobskape-0.0.2.dist-info/METADATA
jobskape-0.0.2.dist-info/WHEEL
jobskape-0.0.2.dist-info/top_level.txt
jobskape-0.0.2.dist-info/RECORD
