Metadata-Version: 2.1
Name: jobskape
Version: 0.0.2
Summary: This is the source code for paper JOBSKAPE: A Framework for Generating Synthetic Job Postings to Enhance Skill Matching (published at NLP4HR Workshop EACL 2024 and now available on ArXiv).
Author: Anna Dai, Syrielle Montariol
Author-email: Antoine Magron <antoine.ja.magron@gmail.com>
Project-URL: Homepage, https://github.com/magantoine/JobSkape/
Classifier: Programming Language :: Python :: 3
Classifier: License :: OSI Approved :: MIT License
Classifier: Operating System :: OS Independent
Requires-Python: >=3.8
License-File: LICENSE
